DA4RDM_RecSys_ContentBased/__init__.py
DA4RDM_RecSys_ContentBased/distance_similarity_calculator.py
DA4RDM_RecSys_ContentBased/preprocessor.py
DA4RDM_RecSys_ContentBased-1.0.10.dist-info/LICENSE
DA4RDM_RecSys_ContentBased-1.0.10.dist-info/METADATA
DA4RDM_RecSys_ContentBased-1.0.10.dist-info/WHEEL
DA4RDM_RecSys_ContentBased-1.0.10.dist-info/top_level.txt
DA4RDM_RecSys_ContentBased-1.0.10.dist-info/RECORD
